{
  "staged_at": "2026-04-08T01:24:00",
  "status": "AWAITING_APPROVAL",
  "deployment_plan": [
    {
      "order": 1,
      "post_id": "R1",
      "subreddit": "r/algotrading",
      "title": "Weekly algo update: Silver breakout strategy (prism-vertex) hitting +11,360 across 90 trades...",
      "scheduled_time": "TBD - await approval",
      "status": "staged",
      "rationale": "Primary target subreddit, performance-focused hook"
    },
    {
      "order": 2,
      "post_id": "R3",
      "subreddit": "r/Daytrading",
      "title": "Daily futures algo check-in: Apr 7 - Which products are you seeing breakout signals on?",
      "scheduled_time": "TBD - await approval",
      "status": "staged",
      "rationale": "Question-driven hook for engagement, larger community"
    },
    {
      "order": 3,
      "post_id": "R4",
      "subreddit": "r/futurestrading",
      "title": "Breakout strategies on futures: Why my Silver algo is beating Nasdaq this week (+11k vs +7k)",
      "scheduled_time": "TBD - await approval",
      "status": "staged",
      "rationale": "Insight-focused, relevant to futures traders"
    }
  ],
  "deployment_rules": {
    "spacing": "Minimum 24 hours between posts to different subreddits",
    "timing": "Post during US market hours (9am-4pm ET) for best engagement",
    "monitor": "Check comments within first 2 hours, respond to questions",
    "abort_conditions": ["Negative reception >50%", "Rule violation flag", "Moderator removal"]
  },
  "approval_required": true,
  "approval_status": "pending"
}
